onboardme/__init__.py
onboardme/config/firewall/iptables.sh
onboardme/config/firewall/ufw/discord
onboardme/console_logging.py
onboardme/constants.py
onboardme/cron.py
onboardme/dot_files.py
onboardme/env_config.py
onboardme/firewall.py
onboardme/help_text.py
onboardme/ide_setup.py
onboardme/misc.py
onboardme/pkg_management.py
onboardme/scripts/update_apt_sources.sh
onboardme/subproc.py
onboardme/sudo_setup.py
onboardme-1.12.3.dist-info/METADATA
onboardme-1.12.3.dist-info/WHEEL
onboardme-1.12.3.dist-info/entry_points.txt
onboardme-1.12.3.dist-info/licenses/LICENSE.txt
onboardme-1.12.3.dist-info/RECORD
