Metadata-Version: 2.4
Name: onboardme
Version: 1.12.3
Summary: Install dot files and packages, including a base mode with sensible defaults to run on most computers running Debian based distros or macOS.
License: AGPL-3.0-or-later
License-File: LICENSE.txt
Keywords: onboardme,onboarding,desktop-setup,development-environment
Author: Jesse Hitch
Author-email: jessebot@linux.com
Requires-Python: >=3.11,<3.14
Classifier: Development Status :: 4 - Beta
Classifier: Intended Audience :: End Users/Desktop
Classifier: License :: OSI Approved :: GNU Affero General Public License v3 or later (AGPLv3+)
Classifier: Operating System :: MacOS :: MacOS X
Classifier: Operating System :: POSIX :: Linux
Classifier: Programming Language :: Python :: 3
Classifier: Programming Language :: Python :: 3.11
Classifier: Programming Language :: Python :: 3.12
Classifier: Programming Language :: Python :: 3.13
Classifier: Topic :: System :: Installation/Setup
Requires-Dist: GitPython (>=3.1,<4.0)
Requires-Dist: PyYAML (>=6.0,<7.0)
Requires-Dist: click (>=8.3,<9.0)
Requires-Dist: rich (>=14.2,<15.0)
Requires-Dist: wget (>=3.2,<4.0)
Requires-Dist: xdg-base-dirs (>=6.0,<7.0)
Project-URL: Bug Tracker, http://git.smallhack.org/jessebot/onboardme/issues
Project-URL: Documentation, https://onboardme.smallhack.org/onboardme
Project-URL: Repository, http://git.smallhack.org/jessebot/onboardme
